toListToArr/__init__.py
toListToArr/arrToList.py
toListToArr/listToArr.py
toListToArr-0.0.1.dist-info/LICENSE
toListToArr-0.0.1.dist-info/METADATA
toListToArr-0.0.1.dist-info/WHEEL
toListToArr-0.0.1.dist-info/top_level.txt
toListToArr-0.0.1.dist-info/RECORD
