Metadata-Version: 2.1
Name: toListToArr
Version: 0.0.1
Summary: Package to convert python linked list to array and Arrays to linked list.
Home-page: https://github.com/pypa/sampleproject
Author: Tathagat
Author-email: tathagatmaitray@gmail.com
Project-URL: Bug Tracker, https://github.com/pypa/sampleproject/issues
Classifier: Programming Language :: Python :: 3
Classifier: License :: OSI Approved :: MIT License
Classifier: Operating System :: OS Independent
Requires-Python: >=3.6
License-File: LICENSE
